squeakily/__init__.py
squeakily/_modidx.py
squeakily/clean.py
squeakily/core.py
squeakily/filter.py
squeakily/helpers.py
squeakily-0.0.2.dist-info/LICENSE
squeakily-0.0.2.dist-info/METADATA
squeakily-0.0.2.dist-info/WHEEL
squeakily-0.0.2.dist-info/entry_points.txt
squeakily-0.0.2.dist-info/top_level.txt
squeakily-0.0.2.dist-info/RECORD
