Metadata-Version: 2.1
Name: squeakily
Version: 0.0.2
Summary: A library for squeakily cleaning and filtering language datasets.
Home-page: https://github.com/CarperAI/squeakily
Author: ncoop57
Author-email: nacooper01@wm.edu
License: Apache Software License 2.0
Keywords: nbdev jupyter notebook python
Classifier: Development Status :: 4 - Beta
Classifier: Intended Audience :: Developers
Classifier: Natural Language :: English
Classifier: Programming Language :: Python :: 3.7
Classifier: Programming Language :: Python :: 3.8
Classifier: Programming Language :: Python :: 3.9
Classifier: Programming Language :: Python :: 3.10
Classifier: License :: OSI Approved :: Apache Software License
Requires-Python: >=3.7
License-File: LICENSE
Requires-Dist: datasketch (==1.5.8)
Requires-Dist: datasets (==2.7.1)
Requires-Dist: Faker (==15.3.3)
Requires-Dist: fastcore
Requires-Dist: networkit
Requires-Dist: rich
Provides-Extra: dev
Requires-Dist: nbdev ; extra == 'dev'
Requires-Dist: scrubadub ; extra == 'dev'
Requires-Dist: twine ; extra == 'dev'
